{
    "asset": {
        "format": "jpg",
        "id": "2ca1bb97c8f21aa434d3a5239520ca56",
        "name": "000327.jpg",
        "path": "file:C:/Users/sreekanth.tammana/Desktop/TrainYourOwnYOLO-master/Data/Source_Images/Training_Images/000327.jpg",
        "size": {
            "width": 320,
            "height": 240
        },
        "state": 2,
        "type": 1
    },
    "regions": [
        {
            "id": "3l51LIb03",
            "type": "RECTANGLE",
            "tags": [
                "person"
            ],
            "boundingBox": {
                "height": 45.806451612903224,
                "width": 25.161290322580644,
                "left": 59.354838709677416,
                "top": 96.12903225806451
            },
            "points": [
                {
                    "x": 59.354838709677416,
                    "y": 96.12903225806451
                },
                {
                    "x": 84.51612903225806,
                    "y": 96.12903225806451
                },
                {
                    "x": 84.51612903225806,
                    "y": 141.93548387096774
                },
                {
                    "x": 59.354838709677416,
                    "y": 141.93548387096774
                }
            ]
        },
        {
            "id": "QWxQUxPLt",
            "type": "RECTANGLE",
            "tags": [
                "person"
            ],
            "boundingBox": {
                "height": 49.67741935483871,
                "width": 26.129032258064516,
                "left": 169.3548387096774,
                "top": 94.19354838709677
            },
            "points": [
                {
                    "x": 169.3548387096774,
                    "y": 94.19354838709677
                },
                {
                    "x": 195.48387096774192,
                    "y": 94.19354838709677
                },
                {
                    "x": 195.48387096774192,
                    "y": 143.8709677419355
                },
                {
                    "x": 169.3548387096774,
                    "y": 143.8709677419355
                }
            ]
        }
    ],
    "version": "2.1.0"
}